setup.py
jenkins_job_builder_clamav/__init__.py
jenkins_job_builder_clamav.egg-info/PKG-INFO
jenkins_job_builder_clamav.egg-info/SOURCES.txt
jenkins_job_builder_clamav.egg-info/dependency_links.txt
jenkins_job_builder_clamav.egg-info/entry_points.txt
jenkins_job_builder_clamav.egg-info/requires.txt
jenkins_job_builder_clamav.egg-info/top_level.txt
jenkins_job_builder_clamav/modules/__init__.py
jenkins_job_builder_clamav/modules/publishers.py